wmi.py
WMI-1.5.data/data/readme.rst
WMI-1.5.data/scripts/wmitest.cmd
WMI-1.5.data/scripts/wmitest.master.ini
WMI-1.5.data/scripts/wmitest.py
WMI-1.5.data/scripts/wmiweb.py
WMI-1.5.dist-info/METADATA
WMI-1.5.dist-info/WHEEL
WMI-1.5.dist-info/top_level.txt
WMI-1.5.dist-info/RECORD
