Metadata-Version: 2.1
Name: WMI
Version: 1.5
Summary: Windows Management Instrumentation
Home-page: http://timgolden.me.uk/python/wmi.html
Author: Tim Golden
Author-email: mail@timgolden.me.uk
License: http://www.opensource.org/licenses/mit-license.php
Platform: UNKNOWN
Requires-Dist: pywin32
Provides-Extra: all
Requires-Dist: pytest ; extra == 'all'
Requires-Dist: twine ; extra == 'all'
Requires-Dist: wheel ; extra == 'all'
Requires-Dist: sphinx ; extra == 'all'
Provides-Extra: dev
Requires-Dist: pytest ; extra == 'dev'
Requires-Dist: sphinx ; extra == 'dev'
Requires-Dist: wheel ; extra == 'dev'
Requires-Dist: twine ; extra == 'dev'
Provides-Extra: docs
Requires-Dist: sphinx ; extra == 'docs'
Provides-Extra: package
Requires-Dist: wheel ; extra == 'package'
Requires-Dist: twine ; extra == 'package'
Provides-Extra: tests
Requires-Dist: pytest ; extra == 'tests'
